MANIFEST.in
README.md
setup.cfg
setup.py
hatshufflepy/hatshufflepy.cpp
hatshufflepy/hatshufflepy.pxd
hatshufflepy/hatshufflepy.pyx
hatshufflepy.egg-info/PKG-INFO
hatshufflepy.egg-info/SOURCES.txt
hatshufflepy.egg-info/dependency_links.txt
hatshufflepy.egg-info/requires.txt
hatshufflepy.egg-info/top_level.txt
hatshufflepy/libhatshuffle/include/depends/ate-pairing/include/bn.h
hatshufflepy/libhatshuffle/include/depends/ate-pairing/include/zm.h
hatshufflepy/libhatshuffle/include/depends/ate-pairing/include/zm2.h
hatshufflepy/libhatshuffle/include/depends/ate-pairing/include/cybozu/benchmark.hpp
hatshufflepy/libhatshuffle/include/depends/ate-pairing/include/cybozu/inttype.hpp
hatshufflepy/libhatshuffle/include/depends/ate-pairing/include/cybozu/test.hpp
hatshufflepy/libhatshuffle/include/libff/algebra/curves/curve_utils.hpp
hatshufflepy/libhatshuffle/include/libff/algebra/curves/curve_utils.tcc
hatshufflepy/libhatshuffle/include/libff/algebra/curves/public_params.hpp
hatshufflepy/libhatshuffle/include/libff/algebra/curves/alt_bn128/alt_bn128_g1.hpp
hatshufflepy/libhatshuffle/include/libff/algebra/curves/alt_bn128/alt_bn128_g2.hpp
hatshufflepy/libhatshuffle/include/libff/algebra/curves/alt_bn128/alt_bn128_init.hpp
hatshufflepy/libhatshuffle/include/libff/algebra/curves/alt_bn128/alt_bn128_pairing.hpp
hatshufflepy/libhatshuffle/include/libff/algebra/curves/alt_bn128/alt_bn128_pp.hpp
hatshufflepy/libhatshuffle/include/libff/algebra/curves/bn128/bn128_g1.hpp
hatshufflepy/libhatshuffle/include/libff/algebra/curves/bn128/bn128_g2.hpp
hatshufflepy/libhatshuffle/include/libff/algebra/curves/bn128/bn128_gt.hpp
hatshufflepy/libhatshuffle/include/libff/algebra/curves/bn128/bn128_init.hpp
hatshufflepy/libhatshuffle/include/libff/algebra/curves/bn128/bn128_pairing.hpp
hatshufflepy/libhatshuffle/include/libff/algebra/curves/bn128/bn128_pp.hpp
hatshufflepy/libhatshuffle/include/libff/algebra/curves/bn128/bn_utils.hpp
hatshufflepy/libhatshuffle/include/libff/algebra/curves/bn128/bn_utils.tcc
hatshufflepy/libhatshuffle/include/libff/algebra/curves/edwards/edwards_g1.hpp
hatshufflepy/libhatshuffle/include/libff/algebra/curves/edwards/edwards_g2.hpp
